{"stats":{"minecraft:killed_by":{"minecraft:creeper":2,"minecraft:piglin":2,"minecraft:zombie":4,"minecraft:spider":2,"minecraft:enderman":1,"minecraft:iron_golem":1,"minecraft:hoglin":4,"minecraft:skeleton":8},"minecraft:custom":{"minecraft:animals_bred":1,"minecraft:interact_with_crafting_table":257,"minecraft:leave_game":19,"minecraft:time_since_death":311070,"minecraft:sprint_one_cm":3056074,"minecraft:damage_blocked_by_shield":1950,"minecraft:drop":295,"minecraft:talked_to_villager":5,"minecraft:play_time":1147358,"minecraft:deaths":41,"minecraft:jump":17823,"minecraft:interact_with_brewingstand":2,"minecraft:walk_on_water_one_cm":43550,"minecraft:interact_with_furnace":303,"minecraft:sleep_in_bed":83,"minecraft:damage_dealt":16807,"minecraft:interact_with_beacon":5,"minecraft:crouch_one_cm":62395,"minecraft:interact_with_smoker":63,"minecraft:use_cauldron":64,"minecraft:inspect_dispenser":15,"minecraft:horse_one_cm":214670,"minecraft:interact_with_smithing_table":2,"minecraft:inspect_dropper":71,"minecraft:mob_kills":82,"minecraft:inspect_hopper":117,"minecraft:fill_cauldron":47,"minecraft:climb_one_cm":143413,"minecraft:walk_one_cm":3451152,"minecraft:damage_dealt_absorbed":2,"minecraft:sneak_time":22867,"minecraft:walk_under_water_one_cm":21460,"minecraft:boat_one_cm":205542,"minecraft:interact_with_blast_furnace":87,"minecraft:total_world_time":624864,"minecraft:interact_with_grindstone":1,"minecraft:time_since_rest":234,"minecraft:damage_taken":20927,"minecraft:minecart_one_cm":386,"minecraft:swim_one_cm":14394,"minecraft:fly_one_cm":2534900,"minecraft:open_chest":885,"minecraft:fish_caught":6,"minecraft:fall_one_cm":473284},"minecraft:mined":{"minecraft:white_bed":1,"minecraft:farmland":4,"minecraft:obsidian":25,"minecraft:granite":8,"minecraft:grass_block":164,"minecraft:hopper":42,"minecraft:nether_wart":10,"minecraft:iron_ore":206,"minecraft:fire":10,"minecraft:target":2,"minecraft:pumpkin":3,"minecraft:pointed_dripstone":2,"minecraft:tripwire":1,"minecraft:crimson_nylium":1,"minecraft:soul_fire":2,"minecraft:torch":6,"minecraft:poppy":3,"minecraft:chest":8,"minecraft:glass":2,"minecraft:nether_quartz_ore":6,"minecraft:cobblestone":107,"minecraft:slime_block":2,"minecraft:oak_planks":3,"minecraft:wall_torch":2,"minecraft:cauldron":19,"minecraft:repeater":8,"minecraft:nether_wart_block":9,"minecraft:birch_log":96,"minecraft:lava_cauldron":2,"minecraft:warped_fungus":1,"minecraft:grass":217,"minecraft:oak_log":112,"minecraft:sand":209,"minecraft:dirt":171,"minecraft:dispenser":3,"minecraft:netherrack":17,"minecraft:piston":4,"minecraft:oak_leaves":47,"minecraft:diamond_ore":10,"minecraft:crimson_roots":5,"minecraft:redstone_wire":7,"minecraft:sandstone":3,"minecraft:redstone_ore":33,"minecraft:nether_sprouts":1,"minecraft:andesite":18,"minecraft:rail":14,"minecraft:stone":668,"minecraft:bone_block":11,"minecraft:comparator":1,"minecraft:lily_of_the_valley":1,"minecraft:observer":15,"minecraft:dandelion":5,"minecraft:oak_fence":1,"minecraft:crafting_table":6,"minecraft:warped_roots":2,"minecraft:rose_bush":2,"minecraft:stone_slab":2,"minecraft:tall_grass":4,"minecraft:diorite":30,"minecraft:redstone_torch":15,"minecraft:birch_leaves":21,"minecraft:coal_ore":62,"minecraft:gravel":1,"minecraft:oak_button":1,"minecraft:stone_bricks":9,"minecraft:gold_ore":6},"minecraft:picked_up":{"minecraft:iron_chestplate":17,"minecraft:wheat":31,"minecraft:stone_slab":10,"minecraft:lead":7,"minecraft:diamond_sword":16,"minecraft:nether_brick":58,"minecraft:string":20,"minecraft:soul_soil":13,"minecraft:iron_leggings":11,"minecraft:sticky_piston":1,"minecraft:pufferfish":2,"minecraft:shroomlight":1,"minecraft:oak_sign":2,"minecraft:diamond_leggings":6,"minecraft:gold_nugget":145,"minecraft:comparator":1,"minecraft:bucket":42,"minecraft:redstone_torch":54,"minecraft:rose_bush":4,"minecraft:iron_pickaxe":15,"minecraft:iron_boots":13,"minecraft:furnace":1,"minecraft:stick":89,"minecraft:oak_fence":2,"minecraft:torch":726,"minecraft:porkchop":23,"minecraft:target":20,"minecraft:diorite":43,"minecraft:pointed_dripstone":104,"minecraft:cauldron":22,"minecraft:stone_sword":12,"minecraft:rotten_flesh":239,"minecraft:blaze_rod":1,"minecraft:cod":4,"minecraft:obsidian":35,"minecraft:cobblestone":2243,"minecraft:birch_log":200,"minecraft:feather":81,"minecraft:repeater":38,"minecraft:andesite":135,"minecraft:potato":136,"minecraft:flint":3,"minecraft:dirt":1131,"minecraft:leather_boots":1,"minecraft:glass":1,"minecraft:bone":34,"minecraft:bow":2,"minecraft:wheat_seeds":24,"minecraft:raw_gold":6,"minecraft:glowstone_dust":7,"minecraft:diamond_helmet":6,"minecraft:oak_planks":49,"minecraft:ghast_tear":1,"minecraft:cooked_porkchop":92,"minecraft:poisonous_potato":3,"minecraft:sand":267,"minecraft:grass_block":2,"minecraft:lily_of_the_valley":1,"minecraft:dispenser":4,"minecraft:slime_block":1,"minecraft:diamond":14,"minecraft:crossbow":4,"minecraft:granite":41,"minecraft:golden_apple":1,"minecraft:bread":2,"minecraft:oak_sapling":16,"minecraft:netherrack":84,"minecraft:diamond_pickaxe":11,"minecraft:fishing_rod":1,"minecraft:charcoal":18,"minecraft:crafting_table":6,"minecraft:chicken":1,"minecraft:nether_wart":12,"minecraft:leather_leggings":3,"minecraft:wooden_pickaxe":2,"minecraft:shield":7,"minecraft:wooden_sword":1,"minecraft:iron_axe":13,"minecraft:flint_and_steel":9,"minecraft:detector_rail":4,"minecraft:beef":1,"minecraft:oak_boat":2,"minecraft:observer":29,"minecraft:poppy":3,"minecraft:minecart":6,"minecraft:chest":11,"minecraft:sugar_cane":1,"minecraft:birch_sapling":11,"minecraft:piston":16,"minecraft:egg":3,"minecraft:raw_iron":100,"minecraft:sandstone":33,"minecraft:stone":110,"minecraft:oak_door":5,"minecraft:carrot":233,"minecraft:redstone":382,"minecraft:netherite_pickaxe":1,"minecraft:arrow":123,"minecraft:weeping_vines":1,"minecraft:diamond_chestplate":6,"minecraft:peony":6,"minecraft:nether_bricks":1,"minecraft:diamond_boots":6,"minecraft:gold_ingot":16,"minecraft:white_wool":159,"minecraft:mutton":2,"minecraft:rail":18,"minecraft:bone_block":32,"minecraft:crimson_stem":1,"minecraft:leather":4,"minecraft:red_mushroom":4,"minecraft:birch_planks":7,"minecraft:oak_log":174,"minecraft:golden_boots":18,"minecraft:nether_wart_block":9,"minecraft:gunpowder":5,"minecraft:cooked_mutton":12,"minecraft:stone_bricks":172,"minecraft:apple":1,"minecraft:iron_ingot":445,"minecraft:stone_pickaxe":25,"minecraft:cooked_chicken":1,"minecraft:iron_ore":127,"minecraft:iron_sword":12,"minecraft:soul_sand":70,"minecraft:oak_slab":4,"minecraft:scaffolding":2,"minecraft:warped_fungus":1,"minecraft:pumpkin":3,"minecraft:quartz":300,"minecraft:dandelion":5,"minecraft:gravel":1,"minecraft:lava_bucket":1,"minecraft:white_bed":2,"minecraft:spider_eye":7,"minecraft:diamond_shovel":1,"minecraft:pumpkin_seeds":16,"minecraft:stone_axe":5,"minecraft:iron_helmet":11,"minecraft:diamond_axe":1,"minecraft:warped_roots":5,"minecraft:oak_button":1,"minecraft:baked_potato":141,"minecraft:coal":354,"minecraft:hopper":46,"minecraft:ender_pearl":1},"minecraft:used":{"minecraft:dispenser":7,"minecraft:poppy":1,"minecraft:chest":21,"minecraft:shield":49,"minecraft:stone":1,"minecraft:iron_sword":366,"minecraft:rotten_flesh":3,"minecraft:lily_of_the_valley":1,"minecraft:carrot":67,"minecraft:weeping_vines":1,"minecraft:obsidian":35,"minecraft:glass":18,"minecraft:lava_bucket":77,"minecraft:hopper_minecart":20,"minecraft:stone_bricks":14,"minecraft:repeater":20,"minecraft:oak_sapling":1,"minecraft:furnace":2,"minecraft:potato":40,"minecraft:diorite":27,"minecraft:diamond_boots":2,"minecraft:dropper":1,"minecraft:stone_pickaxe":441,"minecraft:wooden_pickaxe":56,"minecraft:sand":7,"minecraft:pumpkin_seeds":24,"minecraft:redstone_torch":16,"minecraft:sticky_piston":2,"minecraft:lever":2,"minecraft:string":1,"minecraft:nether_wart_block":2,"minecraft:diamond_sword":230,"minecraft:andesite":7,"minecraft:oak_boat":2,"minecraft:oak_fence":7,"minecraft:rose_bush":1,"minecraft:stone_sword":23,"minecraft:flint_and_steel":4,"minecraft:redstone":29,"minecraft:cooked_chicken":1,"minecraft:netherrack":11,"minecraft:torch":77,"minecraft:dirt":200,"minecraft:target":5,"minecraft:hopper":65,"minecraft:diamond_helmet":2,"minecraft:granite":9,"minecraft:iron_hoe":85,"minecraft:wooden_axe":17,"minecraft:iron_axe":144,"minecraft:slime_block":13,"minecraft:diamond_chestplate":2,"minecraft:minecart":1,"minecraft:netherite_pickaxe":8,"minecraft:cooked_beef":3,"minecraft:pointed_dripstone":35,"minecraft:observer":28,"minecraft:cooked_mutton":4,"minecraft:water_bucket":8,"minecraft:baked_potato":133,"minecraft:cauldron":60,"minecraft:rail":21,"minecraft:comparator":2,"minecraft:crafting_table":12,"minecraft:white_bed":2,"minecraft:piston":9,"minecraft:diamond_pickaxe":718,"minecraft:diamond_shovel":204,"minecraft:chicken":1,"minecraft:oak_button":2,"minecraft:iron_pickaxe":157,"minecraft:netherite_axe":73,"minecraft:stone_slab":3,"minecraft:stone_axe":12,"minecraft:fishing_rod":12,"minecraft:cobblestone":652,"minecraft:cooked_porkchop":29,"minecraft:bucket":81,"minecraft:dandelion":3,"minecraft:diamond_leggings":2},"minecraft:crafted":{"minecraft:oak_planks":416,"minecraft:cooked_chicken":1,"minecraft:slime_block":11,"minecraft:lever":2,"minecraft:cooked_mutton":1,"minecraft:glass":86,"minecraft:hopper":33,"minecraft:repeater":12,"minecraft:bow":4,"minecraft:iron_boots":4,"minecraft:comparator":1,"minecraft:chest":41,"minecraft:oak_button":1,"minecraft:rail":16,"minecraft:oak_fence":6,"minecraft:golden_boots":5,"minecraft:dropper":1,"minecraft:target":4,"minecraft:cauldron":42,"minecraft:cooked_porkchop":2,"minecraft:crafting_table":7,"minecraft:wooden_pickaxe":2,"minecraft:iron_helmet":7,"minecraft:baked_potato":164,"minecraft:sticky_piston":1,"minecraft:hopper_minecart":20,"minecraft:hay_block":5,"minecraft:pumpkin_seeds":8,"minecraft:birch_planks":52,"minecraft:dispenser":4,"minecraft:iron_chestplate":6,"minecraft:diamond_pickaxe":3,"minecraft:shield":5,"minecraft:stone_slab":6,"minecraft:stick":168,"minecraft:iron_ingot":263,"minecraft:iron_pickaxe":9,"minecraft:stone_sword":1,"minecraft:gold_ingot":38,"minecraft:redstone_torch":37,"minecraft:shears":3,"minecraft:fishing_rod":1,"minecraft:furnace":2,"minecraft:piston":7,"minecraft:flint_and_steel":2,"minecraft:iron_axe":4,"minecraft:iron_hoe":2,"minecraft:stone_pickaxe":6,"minecraft:minecart":10,"minecraft:observer":13,"minecraft:wheat":9,"minecraft:cooked_beef":5,"minecraft:diamond_sword":1,"minecraft:iron_sword":6,"minecraft:bucket":29,"minecraft:stone_axe":1,"minecraft:wooden_axe":1,"minecraft:iron_leggings":6,"minecraft:torch":164},"minecraft:broken":{"minecraft:stone_pickaxe":2,"minecraft:iron_sword":1},"minecraft:killed":{"minecraft:zombified_piglin":1,"minecraft:spider":4,"minecraft:skeleton":22,"minecraft:chicken":1,"minecraft:piglin":1,"minecraft:creeper":4,"minecraft:zombie":33,"minecraft:ghast":1,"minecraft:blaze":2,"minecraft:drowned":1,"minecraft:hoglin":4,"minecraft:enderman":2},"minecraft:dropped":{"minecraft:crimson_stem":1,"minecraft:iron_sword":5,"minecraft:porkchop":13,"minecraft:baked_potato":26,"minecraft:diamond":7,"minecraft:cooked_porkchop":21,"minecraft:crossbow":1,"minecraft:dirt":297,"minecraft:dispenser":1,"minecraft:gold_nugget":72,"minecraft:bone_block":12,"minecraft:iron_pickaxe":6,"minecraft:white_wool":2,"minecraft:cauldron":2,"minecraft:gold_ingot":28,"minecraft:bone":1,"minecraft:nether_brick":26,"minecraft:birch_sapling":1,"minecraft:rotten_flesh":78,"minecraft:oak_planks":6,"minecraft:cooked_mutton":3,"minecraft:carrot":1,"minecraft:hopper":1,"minecraft:leather_leggings":1,"minecraft:iron_ore":8,"minecraft:arrow":22,"minecraft:scaffolding":1,"minecraft:netherrack":1,"minecraft:egg":1,"minecraft:iron_ingot":81,"minecraft:golden_boots":6,"minecraft:netherite_pickaxe":1,"minecraft:wheat_seeds":3,"minecraft:cobblestone":54,"minecraft:iron_helmet":7,"minecraft:observer":1,"minecraft:grass_block":2,"minecraft:coal":3,"minecraft:stick":10,"minecraft:diorite":2,"minecraft:torch":140,"minecraft:nether_wart_block":5,"minecraft:iron_leggings":5,"minecraft:iron_axe":2,"minecraft:bucket":30,"minecraft:redstone":1,"minecraft:iron_boots":4,"minecraft:stone_slab":5,"minecraft:diamond_sword":4,"minecraft:potato":1,"minecraft:stone":3,"minecraft:shield":3,"minecraft:iron_chestplate":7,"minecraft:diamond_pickaxe":1,"minecraft:redstone_torch":1,"minecraft:spider_eye":2,"minecraft:bow":1}},"DataVersion":2724}